mosviz/__init__.py
mosviz/_astropy_init.py
mosviz/cli.py
mosviz/conftest.py
mosviz/mosviz_data_factory.py
mosviz/startup.py
mosviz/controls/__init__.py
mosviz/controls/slits/__init__.py
mosviz/controls/slits/rectangle_slit.py
mosviz/controls/slits/saved_slits.yaml
mosviz/controls/slits/slit_base.py
mosviz/controls/slits/slit_controller.py
mosviz/controls/slits/slit_selection_ui.py
mosviz/controls/tests/__init__.py
mosviz/controls/tests/test_slit_controller.py
mosviz/data/resources/mosviz_icon.png
mosviz/data/resources/mosviz_logo.png
mosviz/data/resources/mosviz_splash.png
mosviz/data/resources/slit_icon.png
mosviz/data/ui/layer_widget.ui
mosviz/data/ui/loader_selection.ui
mosviz/data/ui/mos_widget.ui
mosviz/data/ui/icons/External-96.png
mosviz/data/ui/icons/Next-96.png
mosviz/data/ui/icons/Previous-96.png
mosviz/data/ui/icons/Settings-96.png
mosviz/extern/__init__.py
mosviz/loaders/__init__.py
mosviz/loaders/deimos_loaders.py
mosviz/loaders/hst_loaders.py
mosviz/loaders/jwst_loaders.py
mosviz/loaders/loader_selection.py
mosviz/loaders/utils.py
mosviz/loaders/tests/__init__.py
mosviz/loaders/tests/test_load_NIRSpec_data.py
mosviz/loaders/tests/test_mos_loaders.py
mosviz/loaders/tests/data/__init__.py
mosviz/loaders/tests/data/deimos/12004808.acs.v_6ac_.fits.gz
mosviz/loaders/tests/data/deimos/__init__.py
mosviz/loaders/tests/data/deimos/slit.1153.151R.fits.gz
mosviz/loaders/tests/data/deimos/spec1d.1153.151.12004808.fits.gz
mosviz/loaders/tests/data/jwst/2Dspectrum_MOS_1_105_039_CLEAR-PRISM_MOS_PRISM-observation-2-c0e0_000.fits.gz
mosviz/loaders/tests/data/jwst/Final_spectrum_MOS_1_105_039_CLEAR-PRISM_MOS_PRISM-observation-2-c0e0_000.fits.gz
mosviz/loaders/tests/data/jwst/__init__.py
mosviz/loaders/tests/data/jwst/nrc_oct16_969.fits.gz
mosviz/plugins/__init__.py
mosviz/plugins/cutout_tool/__init__.py
mosviz/plugins/cutout_tool/cutout_lib.py
mosviz/plugins/cutout_tool/cutout_tool.py
mosviz/plugins/cutout_tool/tests/__init__.py
mosviz-0.3.1.dist-info/LICENSE.rst
mosviz-0.3.1.dist-info/METADATA
mosviz-0.3.1.dist-info/WHEEL
mosviz-0.3.1.dist-info/entry_points.txt
mosviz-0.3.1.dist-info/top_level.txt
mosviz-0.3.1.dist-info/RECORD
