Metadata-Version: 2.1
Name: mosviz
Version: 0.3.1
Summary: MOS visualization tool
Home-page: https://github.com/spacetelescope/mosviz
Author: JDADF Developers
License: BSD 3-Clause
Platform: UNKNOWN
Provides: mosviz
Requires-Python: >=3.6
License-File: licenses/LICENSE.rst
Requires-Dist: numpy (>=1.16)
Requires-Dist: astropy (>=3.1)
Requires-Dist: glue-core (>=0.14)
Requires-Dist: regions (>=0.3)
Requires-Dist: specviz (>=0.7.0)
Requires-Dist: qtpy
Requires-Dist: pyqt5 (==5.12.3)
Requires-Dist: pyqtgraph (==0.10.0)
Requires-Dist: reproject
Provides-Extra: tests
Requires-Dist: pytest-astropy ; extra == 'tests'
